[
  {
    "id": "1",
    "title": "Buxar Radio Br-44",
    "image": "https://i.postimg.cc/Y0BggqJs/Chat-GPT-Image-Mar-31-2025-11-22-49-AM.png",
    "streamUrl": "https://stream-153.zeno.fm/s6vu9rzucfhvv"
  },
  {
    "id": "2",
    "title": "Bhakti Sagar Radio",
    "image": "https://i.postimg.cc/Y0BggqJs/Chat-GPT-Image-Mar-31-2025-11-22-49-AM.png",
    "streamUrl": "https://stream.zeno.fm/lcida9v81nmvv"
  },
  {
    "id": "3",
    "title": "Krishna Bhakti Radio",
    "image": "https://i.postimg.cc/Y0BggqJs/Chat-GPT-Image-Mar-31-2025-11-22-49-AM.png",
    "streamUrl": "http://stream.zeno.fm/nqvcaqevkx5vv"
  },
  {
    "id": "4",
    "title": "Bhojpuri Bhakti Radio",
    "image": "https://i.postimg.cc/Y0BggqJs/Chat-GPT-Image-Mar-31-2025-11-22-49-AM.png",
    "streamUrl": "https://stream.zeno.fm/jqmyjaoycfkvv"
  },
  {
    "id": "5",
    "title": "Bhagwat Geeta Radio",
    "image": "https://i.postimg.cc/Y0BggqJs/Chat-GPT-Image-Mar-31-2025-11-22-49-AM.png",
    "streamUrl": "http://stream.zeno.fm/nqvcaqevkx5vv"
  },
  {
    "id": "6",
    "title": "Anant Prakash Radio",
    "image": "https://i.postimg.cc/Y0BggqJs/Chat-GPT-Image-Mar-31-2025-11-22-49-AM.png",
    "streamUrl": "https://stream.zeno.fm/trpnbue9huhvv"
  }
]
